offlog/__init__.py
offlog/__main__.py
offlog/client.py
offlog/logger.py
offlog/server.py
offlog-0.3.1.dist-info/LICENSE.txt
offlog-0.3.1.dist-info/METADATA
offlog-0.3.1.dist-info/WHEEL
offlog-0.3.1.dist-info/top_level.txt
offlog-0.3.1.dist-info/zip-safe
offlog-0.3.1.dist-info/RECORD
