Metadata-Version: 2.1
Name: offlog
Version: 0.3.1
Summary: A non-blocking file-append service for Unix systems
Home-page: https://github.com/chrisjbillington/offlog
Author: Christopher Billington
Author-email: chrisjbillington@gmail.com
License: MIT
Project-URL: Source Code, https://github.com/chrisjbillington/offlog
Project-URL: Download, https://pypi.org/project/offlog/
Project-URL: Tracker, https://github.com/chrisjbillington/offlog/issues
Keywords: logging unix
Classifier: License :: OSI Approved :: MIT License
Classifier: Programming Language :: Python :: 3 :: Only
Requires-Python: >=3.7
License-File: LICENSE.txt
